simulation/__init__.py
simulation/framework.py
simulation/types.py
discrete_event_simulation-0.1.2.dist-info/LICENSE
discrete_event_simulation-0.1.2.dist-info/METADATA
discrete_event_simulation-0.1.2.dist-info/WHEEL
discrete_event_simulation-0.1.2.dist-info/top_level.txt
discrete_event_simulation-0.1.2.dist-info/RECORD
