Metadata-Version: 2.1
Name: discrete-event-simulation
Version: 0.1.2
Summary: Framework for making discrete event simulations
Home-page: https://github.com/AlexanderGrooff/discrete-event-simulation
Author: Alexander Grooff
Author-email: alexandergrooff@gmail.com
License: UNKNOWN
Platform: UNKNOWN
Classifier: Programming Language :: Python :: 3
Classifier: License :: OSI Approved :: MIT License
Classifier: Operating System :: OS Independent
Requires-Python: >=3.8
